.gitignore
MANIFEST.in
README.rst
setup.py
collective/__init__.py
collective.zodbdebug.egg-info/PKG-INFO
collective.zodbdebug.egg-info/SOURCES.txt
collective.zodbdebug.egg-info/dependency_links.txt
collective.zodbdebug.egg-info/entry_points.txt
collective.zodbdebug.egg-info/namespace_packages.txt
collective.zodbdebug.egg-info/not-zip-safe
collective.zodbdebug.egg-info/requires.txt
collective.zodbdebug.egg-info/top_level.txt
collective/zodbdebug/__init__.py
collective/zodbdebug/config.py
collective/zodbdebug/configure.zcml
collective/zodbdebug/core.py
collective/zodbdebug/util.py
collective/zodbdebug/scripts/__init__.py
collective/zodbdebug/scripts/scan_blobs.py
collective/zodbdebug/scripts/show_transactions.py
docs/HISTORY.rst