Metadata-Version: 1.1
Name: collective.zodbdebug
Version: 0.0.1
Summary: Tools to debug a ZODB.
Home-page: https://github.com/collective/collective.zodbdebug
Author: Rafael Oliveira
Author-email: rafaelbco@gmail.com
License: GPL
Keywords: zope zodb debug
Platform: UNKNOWN
Classifier: Framework :: ZODB
Classifier: Framework :: Zope :: 2
Classifier: Framework :: Zope
Classifier: Framework :: Zope2
Classifier: License :: OSI Approved :: GNU General Public License (GPL)
Classifier: Programming Language :: Python :: 2.7
Classifier: Programming Language :: Python
